packmaker/__init__.py
packmaker/download.py
packmaker/fabric.py
packmaker/forge.py
packmaker/libraries.py
packmaker/main.py
packmaker/minecraft.py
packmaker/modloader.py
packmaker/packdef.py
packmaker/packlock.py
packmaker/resolver.py
packmaker/builder/__init__.py
packmaker/builder/base.py
packmaker/builder/curseforge.py
packmaker/builder/local.py
packmaker/builder/pack.py
packmaker/builder/routhio.py
packmaker/builder/server.py
packmaker/cmd/__init__.py
packmaker/cmd/apidebug.py
packmaker/cmd/build.py
packmaker/cmd/convert.py
packmaker/cmd/findupdates.py
packmaker/cmd/info.py
packmaker/cmd/launch.py
packmaker/cmd/lock.py
packmaker/cmd/modsinfo.py
packmaker/cmd/resourcepacksinfo.py
packmaker/cmd/search.py
packmaker/cmd/updatedb.py
packmaker/curse/__init__.py
packmaker/curse/api.py
packmaker/curse/curseforge.py
packmaker/curse/cursemeta.py
packmaker/framew/__init__.py
packmaker/framew/application.py
packmaker/framew/baseobject.py
packmaker/framew/cmdapplication.py
packmaker/framew/config.py
packmaker/framew/formatter.py
packmaker/framew/log.py
packmaker/framew/outputter.py
packmaker/framew/string_conversion.py
tests/mockapi/__init__.py
packmaker-0.10.0.dist-info/LICENSE
packmaker-0.10.0.dist-info/METADATA
packmaker-0.10.0.dist-info/WHEEL
packmaker-0.10.0.dist-info/entry_points.txt
packmaker-0.10.0.dist-info/top_level.txt
packmaker-0.10.0.dist-info/RECORD
