Metadata-Version: 2.1
Name: packmaker
Version: 0.10.0
Summary: minecraft modpack maker
Home-page: https://packmaker.readthedocs.io
Author: Mark Crewson
Author-email: mark@crewson.net
Keywords: minecraft modded modpack
Classifier: Development Status :: 4 - Beta
Classifier: Environment :: Console
Classifier: License :: OSI Approved :: Apache Software License
Classifier: Operating System :: MacOS :: MacOS X
Classifier: Operating System :: Microsoft :: Windows
Classifier: Operating System :: POSIX :: Linux
Classifier: Programming Language :: Python :: 3
Classifier: Topic :: Games/Entertainment
Requires-Python: >=3.6
License-File: LICENSE
Requires-Dist: aiohttp (==3.7.3)
Requires-Dist: chardet (==3.0.4)
Requires-Dist: jinja2
Requires-Dist: prettytable
Requires-Dist: python-dateutil
Requires-Dist: pyyaml
Requires-Dist: requests
Requires-Dist: requests-cache
Requires-Dist: urllib3
